chatgpt_gui/__init__.py
chatgpt_gui/__main__.py
chatgpt_gui/_version.py
chatgpt_gui/constants.py
chatgpt_gui/events.py
chatgpt_gui/exception_hook.py
chatgpt_gui/lang.py
chatgpt_gui/models.py
chatgpt_gui/py.typed
chatgpt_gui/run.py
chatgpt_gui/tomlfile.py
chatgpt_gui/_vendor/__init__.py
chatgpt_gui/_vendor/packaging/__init__.py
chatgpt_gui/_vendor/packaging/_structures.py
chatgpt_gui/_vendor/packaging/version.py
chatgpt_gui/gui/__init__.py
chatgpt_gui/gui/aliases.py
chatgpt_gui/gui/app.py
chatgpt_gui/gui/workers.py
chatgpt_gui/gui/menus/__init__.py
chatgpt_gui/gui/menus/account.py
chatgpt_gui/gui/menus/conversations.py
chatgpt_gui/gui/menus/help.py
chatgpt_gui/gui/menus/tools.py
chatgpt_gui/gui/widgets/__init__.py
chatgpt_gui/gui/widgets/combo_box.py
chatgpt_gui/gui/widgets/conversation_tabs.py
chatgpt_gui/gui/widgets/conversation_view.py
chatgpt_gui/gui/widgets/exception_logger.py
chatgpt_gui/gui/widgets/external_text_browser.py
chatgpt_gui/gui/widgets/paste_line_edit.py
chatgpt_gui/gui/windows/__init__.py
chatgpt_gui/gui/windows/application.py
chatgpt_gui/gui/windows/captcha_dialog.py
chatgpt_gui/gui/windows/changelog_viewer.py
chatgpt_gui/gui/windows/exception_reporter.py
chatgpt_gui/gui/windows/license_viewer.py
chatgpt_gui/gui/windows/readme_viewer.py
chatgpt_gui/gui/windows/settings.py
chatgpt_gui/gui/windows/sign_in_dialog.py
chatgpt_gui/network/__init__.py
chatgpt_gui/network/manager.py
chatgpt_gui/network/version_check.py
chatgpt_gui/network/client/__init__.py
chatgpt_gui/network/client/auth.py
chatgpt_gui/network/client/chatgpt.py
chatgpt_gui/network/client/structures.py
chatgpt_gui/resources/default_settings.toml
chatgpt_gui/resources/external_icons.json
chatgpt_gui/resources/icons/about.png
chatgpt_gui/resources/icons/account.png
chatgpt_gui/resources/icons/add.png
chatgpt_gui/resources/icons/captcha.png
chatgpt_gui/resources/icons/copyright.png
chatgpt_gui/resources/icons/openai.ico
chatgpt_gui/resources/icons/settings.png
chatgpt_gui-0.4.1.dist-info/entry_points.txt
chatgpt_gui-0.4.1.dist-info/LICENSE
chatgpt_gui-0.4.1.dist-info/WHEEL
chatgpt_gui-0.4.1.dist-info/METADATA
chatgpt_gui-0.4.1.dist-info/RECORD
