Metadata-Version: 2.1
Name: chatgpt-gui
Version: 0.4.1
Summary: An unofficial GUI app for ChatGPT.
Keywords: ai,gpt,gui,app,client,unofficial,ChatGPT
Author-email: Cubicpath <cubicpath@pm.me>
Requires-Python: >=3.10
Classifier: Development Status :: 3 - Alpha
Classifier: Environment :: X11 Applications :: Qt
Classifier: Intended Audience :: End Users/Desktop
Classifier: License :: OSI Approved :: MIT License
Classifier: Natural Language :: English
Classifier: Operating System :: OS Independent
Classifier: Programming Language :: Python :: 3 :: Only
Classifier: Programming Language :: Python :: 3.10
Classifier: Programming Language :: Python :: 3.11
Classifier: Topic :: Internet :: WWW/HTTP
Classifier: Topic :: Software Development :: User Interfaces
Classifier: Typing :: Typed
Requires-Dist: PySide6-Essentials>=6.4.1
Requires-Dist: toml>=0.10.2
Requires-Dist: tls-client>=0.1.5
Requires-Dist: undetected-chromedriver>=3.1.7
Requires-Dist: beautifulsoup4>=4.11.1
Requires-Dist: python-dotenv>=0.21.0 ; extra == "all"
Requires-Dist: autopep8>=2.0.1 ; extra == "dev"
Requires-Dist: bandit>=1.7.4 ; extra == "dev"
Requires-Dist: pylint>=2.15.8 ; extra == "dev"
Requires-Dist: pyright>=1.1.284 ; extra == "dev"
Project-URL: Issue Tracker, https://github.com/Cubicpath/ChatGPT-GUI/issues
Project-URL: Source Code, https://github.com/Cubicpath/ChatGPT-GUI
Provides-Extra: all
Provides-Extra: dev
